ambition_utils/__init__.py
ambition_utils/apps.py
ambition_utils/fields.py
ambition_utils/forms.py
ambition_utils/sql.py
ambition_utils/time_helpers.py
ambition_utils/urls.py
ambition_utils/version.py
ambition_utils/activity/__init__.py
ambition_utils/activity/models.py
ambition_utils/activity/tasks.py
ambition_utils/activity/migrations/0001_initial.py
ambition_utils/activity/migrations/0002_auto_20180427_1819.py
ambition_utils/activity/migrations/__init__.py
ambition_utils/activity/tests/__init__.py
ambition_utils/activity/tests/model_tests.py
ambition_utils/activity/tests/task_tests.py
ambition_utils/anomaly/__init__.py
ambition_utils/anomaly/models.py
ambition_utils/anomaly/tests/__init__.py
ambition_utils/anomaly/tests/anomaly_tests.py
ambition_utils/anomaly/tests/apps.py
ambition_utils/anomaly/tests/models.py
ambition_utils/anomaly/tests/migrations/0001_initial.py
ambition_utils/anomaly/tests/migrations/__init__.py
ambition_utils/postgres_lock/__init__.py
ambition_utils/postgres_lock/lock.py
ambition_utils/postgres_lock/models.py
ambition_utils/postgres_lock/migrations/0001_initial.py
ambition_utils/postgres_lock/migrations/0002_auto_20191030_1417.py
ambition_utils/postgres_lock/migrations/0003_auto_20220525_1754.py
ambition_utils/postgres_lock/migrations/__init__.py
ambition_utils/postgres_lock/tests/__init__.py
ambition_utils/postgres_lock/tests/lock_tests.py
ambition_utils/rrule/__init__.py
ambition_utils/rrule/apps.py
ambition_utils/rrule/constants.py
ambition_utils/rrule/forms.py
ambition_utils/rrule/handler.py
ambition_utils/rrule/models.py
ambition_utils/rrule/migrations/0001_initial.py
ambition_utils/rrule/migrations/0002_auto_20190422_2037.py
ambition_utils/rrule/migrations/0003_auto_20220623_1649.py
ambition_utils/rrule/migrations/0004_rrule_rrule_exclusion_params.py
ambition_utils/rrule/migrations/0005_auto_20230802_1548.py
ambition_utils/rrule/migrations/0006_rrule_time_last_handled.py
ambition_utils/rrule/migrations/__init__.py
ambition_utils-3.2.2.dist-info/LICENSE
ambition_utils-3.2.2.dist-info/METADATA
ambition_utils-3.2.2.dist-info/WHEEL
ambition_utils-3.2.2.dist-info/top_level.txt
ambition_utils-3.2.2.dist-info/RECORD
