Metadata-Version: 2.1
Name: ambition-utils
Version: 3.2.2
Summary: Various utility packages used across Ambition projects.
Home-page: https://github.com/ambitioninc/ambition-utils
Author: Wes Okes
Author-email: wes.okes@gmail.com
License: MIT
Keywords: django,database,query,sql,postgres,upsert
Platform: UNKNOWN
Classifier: Programming Language :: Python
Classifier: Programming Language :: Python :: 3.10
Classifier: Programming Language :: Python :: 3.11
Classifier: Intended Audience :: Developers
Classifier: License :: OSI Approved :: MIT License
Classifier: Operating System :: OS Independent
Classifier: Framework :: Django
Classifier: Framework :: Django :: 4.2
Classifier: Framework :: Django :: 5.1
License-File: LICENSE
Requires-Dist: django-timezone-field<6
Requires-Dist: fleming>=0.7.0
Requires-Dist: django-manager-utils>=3.0.1
Requires-Dist: Django>=3.2
Requires-Dist: pandas>=0.21.0
Requires-Dist: python-dateutil>=2.4.2
Requires-Dist: pytz>=2015.6
Requires-Dist: sqlparse
Requires-Dist: tdigest
Requires-Dist: wrapt>=1.10.5
Provides-Extra: dev
Requires-Dist: celery>=5.2.2; extra == "dev"
Requires-Dist: coverage; extra == "dev"
Requires-Dist: coveralls; extra == "dev"
Requires-Dist: django-nose; extra == "dev"
Requires-Dist: django-dynamic-fixture>=2.0.0; extra == "dev"
Requires-Dist: freezegun; extra == "dev"
Requires-Dist: psycopg2; extra == "dev"
Requires-Dist: flake8; extra == "dev"
